zagency/__init__.py
zagency/advanced/__init__.py
zagency/advanced/improving_agent.py
zagency/advanced/tool_dir_agent.py
zagency/core/__init__.py
zagency/core/agent.py
zagency/core/base.py
zagency/core/environment.py
zagency/core/evaluation.py
zagency/core/lm.py
zagency/core/scorer.py
zagency/core/template_loader.py
zagency/environments/coding_environment.py
zagency-0.6.5.dist-info/METADATA
zagency-0.6.5.dist-info/WHEEL
zagency-0.6.5.dist-info/top_level.txt
zagency-0.6.5.dist-info/RECORD
