Metadata-Version: 2.4
Name: zagency
Version: 0.6.5
Summary: An agentic framework for building AI agents with LLM integration
Author-email: zubin <zubin@email.com>
License: MIT
Project-URL: Homepage, https://github.com/lowercaselabs/zagency
Project-URL: Repository, https://github.com/lowercaselabs/zagency
Project-URL: Issues, https://github.com/lowercaselabs/zagency/issues
Classifier: Development Status :: 3 - Alpha
Classifier: Intended Audience :: Developers
Classifier: License :: OSI Approved :: MIT License
Classifier: Programming Language :: Python :: 3
Classifier: Programming Language :: Python :: 3.8
Classifier: Programming Language :: Python :: 3.9
Classifier: Programming Language :: Python :: 3.10
Classifier: Programming Language :: Python :: 3.11
Classifier: Programming Language :: Python :: 3.12
Requires-Python: >=3.8
Requires-Dist: torch
Requires-Dist: whisper
Requires-Dist: pyannote.audio
Requires-Dist: ffmpeg-python
Requires-Dist: litellm
Requires-Dist: rich
Requires-Dist: pydantic
